setup.py
src/lanyon/__init__.py
src/lanyon/app.py
src/lanyon/autoreload.py
src/lanyon/parser.py
src/lanyon/server.py
src/lanyon/template.py
src/lanyon/url.py
src/lanyon/utils.py
src/lanyon.egg-info/PKG-INFO
src/lanyon.egg-info/SOURCES.txt
src/lanyon.egg-info/dependency_links.txt
src/lanyon.egg-info/entry_points.txt
src/lanyon.egg-info/not-zip-safe
src/lanyon.egg-info/requires.txt
src/lanyon.egg-info/top_level.txt