Metadata-Version: 1.0
Name: lanyon
Version: 6
Summary: Static Site Generator
Home-page: http://bitbucket.org/arthurk/lanyon/
Author: Arthur Koziel
Author-email: UNKNOWN
License: BSD
Platform: UNKNOWN
